Metadata-Version: 2.1
Name: scraping-link
Version: 0.0.7
Summary: A Python module for web scraping
Home-page: https://github.com/nicolasmarin/scraping-link-python
Author: nicolasmarin
Author-email: info@scraping.link
License: GPLv3
Download-URL: https://github.com/nicolasmarin/scraping-link-python/archive/refs/heads/main.zip
Keywords: web scraping,scraping,proxy rotating,html
Platform: UNKNOWN
Classifier: Programming Language :: Python :: 3
Classifier: Operating System :: OS Independent
Classifier: Topic :: Software Development :: Build Tools
Classifier: License :: OSI Approved :: GNU General Public License v3 (GPLv3)
